fabric_virtualenv-0.3.0.dist-info/WHEEL
fabric_virtualenv-0.3.0.dist-info/top_level.txt
fabric_virtualenv-0.3.0.dist-info/metadata.json
fabric_virtualenv-0.3.0.dist-info/RECORD
fabric_virtualenv-0.3.0.dist-info/DESCRIPTION.rst
fabric_virtualenv-0.3.0.dist-info/METADATA
fabvenv/__init__.py
