Metadata-Version: 2.0
Name: fabric-virtualenv
Version: 0.3.0
Summary: Some additional functions for working with remote virtualenvs in Fabric.
Home-page: http://pypi.python.org/pypi/fabric-virtualenv/
Author: Daniel Pope
Author-email: lord.mauve@gmail.com
License: UNKNOWN
Platform: UNKNOWN
Requires-Dist: Fabric
